timerdecor
